{
  "id": "2023-09-04T16:29:48.076Z0.17441914482263599",
  "alert": "Start of result\nResult\n\nMinimum yearly repayment met.\n\nThe amount of the loan not repaid at the end of income year 2020-21 is $54.65.\n\nThe amalgamated loan will not be taken to be a dividend because the total repayments made are equal to or greater than the minimum yearly repayment required for income year 2020-21.\n\nInterest received by the private company must be included in the income tax return for 2020-21.\n\nMinimum yearly repayment\n\n$3,421.00\n\nBenchmark interest rate\n\n4.52%\n\nOpening balance:\n\nDate: 30/06/2020\n\nBalance: $9,400.00\n\nDays: 0\n\nInterest: $0\n\nPayments\n\nDate: 01/07/2020\n\nAmount: $1,878.00\n\nBalance: $7,522.00\n\nDays: 7\n\nInterest: $6.52\n\n\n\n\nDate: 08/07/2020\n\nAmount: $2,026.00\n\nBalance: $5,496.00\n\nDays: 60\n\nInterest: $40.84\n\n\n\n\nDate: 06/09/2020\n\nAmount: $3,861.00\n\nBalance: $1,635.00\n\nDays: 36\n\nInterest: $7.29\n\n\n\n\nDate: 12/10/2020\n\nAmount: $1,635.00\n\nBalance: $0\n\nDays: 262\n\nInterest: $0\n\n\n\n\nTotal repayments\n\n$9,400.00\n\nTotal interest\n\n$54.65\n\nTotal principal\n\n$9,345.35\n\nClosing balance\n\nDate: 30/06/2021\n\nBalance: $54.65",
  "outputs": {
    "enquiryRateFormatted": "4.52%",
    "enquiryYearEndMinusOneDisplay": "30/06/2020",
    "amalgamatedLoanNotPaidByEOIYFormatted": "$9,400.00",
    "openingBalancePayDays": "0",
    "openingBalanceInterestFormatted": "$0",
    "totalAmountOfRepaymentFormatted": "$9,400.00",
    "totalInterestFormatted": "$54.65",
    "principalFormatted": "$9,345.35",
    "enquiryYearEndDisplay": "30/06/2021",
    "minimumYearRepaymentFormatted": "$3,421.00"
  },
  "repayments": [
    {
      "rd": "1/7/2020",
      "ra": 1878
    },
    {
      "rd": "8/7/2020",
      "ra": 2026
    },
    {
      "rd": "6/9/2020",
      "ra": 3861
    },
    {
      "rd": "12/10/2020",
      "ra": 1635
    }
  ],
  "inputs": {
    "incomeYearOfLoan": 2018,
    "fullTermOfAmalgamatedLoan": 5,
    "incomeYearOfEnquiring": 2021,
    "amalgamatedLoanNotPaidByEOIY": 9400,
    "repayments": null,
    "lodgement_date": null
  },
  "idx": 633
}