{
  "id": "2023-10-31T20:48:08.321Z0.19199796399032887",
  "alert": "Start of result\nResult\n\nAmalgamated loan fully repaid.\n\nThe amalgamated loan has been paid in full.\u000bThe private company is not taken under Division 7A to pay a dividend to the shareholder or shareholder's associate.\n\nInterest received by the private company must be included in the income tax return for 1999-00.\n\nMinimum yearly repayment\n\n$63.00\n\nBenchmark interest rate\n\n6.5%\n\nOpening balance:\n\nDate: 30/06/1999\n\nBalance: $59.43\n\nDays: 133\n\nInterest: $1.40\n\nPayments\n\nDate: 11/11/1999\n\nAmount: $231.00\n\nBalance: $0\n\nDays: 233\n\nInterest: $0\n\n\n\n\nTotal repayments\n\n$231.00\n\nTotal interest\n\n$1.40\n\nTotal principal\n\n$229.60\n\nClosing balance\n\nDate: 30/06/2000\n\nBalance: $0",
  "outputs": {
    "enquiryRateFormatted": "6.5%",
    "enquiryYearEndMinusOneDisplay": "30/06/1999",
    "amalgamatedLoanNotPaidByEOIYFormatted": "$59.43",
    "openingBalancePayDays": "133",
    "openingBalanceInterestFormatted": "$1.40",
    "totalAmountOfRepaymentFormatted": "$231.00",
    "totalInterestFormatted": "$1.40",
    "principalFormatted": "$229.60",
    "enquiryYearEndDisplay": "30/06/2000",
    "minimumYearRepaymentFormatted": "$63.00",
    "loanAmountFormatted": "$0"
  },
  "repayments": [
    {
      "rd": "11/11/1999",
      "ra": 231
    }
  ],
  "inputs": {
    "incomeYearOfLoan": 1999,
    "fullTermOfAmalgamatedLoan": 1,
    "incomeYearOfEnquiring": 2000,
    "amalgamatedLoanNotPaidByEOIY": 59.4312657543249,
    "repayments": null,
    "lodgement_date": "31/7/1999"
  },
  "idx": 6773
}