{
  "id": "2023-10-31T18:32:00.097Z0.4393288419226675",
  "alert": "Start of result\nResult\n\nAmalgamated loan fully repaid.\n\nThe amalgamated loan has been paid in full.\u000bThe private company is not taken under Division 7A to pay a dividend to the shareholder or shareholder's associate.\n\nInterest received by the private company must be included in the income tax return for 2014-15.\n\nMinimum yearly repayment\n\n$27.00\n\nBenchmark interest rate\n\n5.95%\n\nOpening balance:\n\nDate: 30/06/2014\n\nBalance: $25.66\n\nDays: 15\n\nInterest: $0.06\n\nPayments\n\nDate: 16/07/2014\n\nAmount: $256.62\n\nBalance: $0\n\nDays: 350\n\nInterest: $0\n\n\n\n\nTotal repayments\n\n$256.62\n\nTotal interest\n\n$0.06\n\nTotal principal\n\n$256.56\n\nClosing balance\n\nDate: 30/06/2015\n\nBalance: $0",
  "outputs": {
    "enquiryRateFormatted": "5.95%",
    "enquiryYearEndMinusOneDisplay": "30/06/2014",
    "amalgamatedLoanNotPaidByEOIYFormatted": "$25.66",
    "openingBalancePayDays": "15",
    "openingBalanceInterestFormatted": "$0.06",
    "totalAmountOfRepaymentFormatted": "$256.62",
    "totalInterestFormatted": "$0.06",
    "principalFormatted": "$256.56",
    "enquiryYearEndDisplay": "30/06/2015",
    "minimumYearRepaymentFormatted": "$27.00",
    "loanAmountFormatted": "$0"
  },
  "repayments": [
    {
      "rd": "16/7/2014",
      "ra": 256.62433748647163
    }
  ],
  "inputs": {
    "incomeYearOfLoan": 2009,
    "fullTermOfAmalgamatedLoan": 6,
    "incomeYearOfEnquiring": 2015,
    "amalgamatedLoanNotPaidByEOIY": 25.662433748647253,
    "repayments": null,
    "lodgement_date": null
  },
  "idx": 4133
}