{
  "id": "2023-09-06T08:11:03.103Z0.8638156027169075",
  "alert": "Start of result\nResult\n\nMinimum yearly repayment not met.\n\nThe amount of the loan not repaid at the end of income year 2014-15 is $2.03.\n\nThe private company may be taken to pay a dividend under Division 7A to the shareholder or shareholder's associate because the amount repaid during income year 2014-15 in relation to the amalgamated loan is less than the minimum yearly repayment required.\n\nInterest received by the private company must be included in the income tax return for 2014-15.\n\nMinimum yearly repayment\n\n$42.00\n\nBenchmark interest rate\n\n5.95%\n\nOpening balance:\n\nDate: 30/06/2014\n\nBalance: $39.48\n\nDays: 315\n\nInterest: $2.03\n\nPayments\n\nDate: 12/05/2015\n\nAmount: $39.48\n\nBalance: $0\n\nDays: 50\n\nInterest: $0\n\n\n\n\nTotal repayments\n\n$39.48\n\nTotal interest\n\n$2.03\n\nTotal principal\n\n$37.45\n\nClosing balance\n\nDate: 30/06/2015\n\nBalance: $2.03",
  "outputs": {
    "enquiryRateFormatted": "5.95%",
    "enquiryYearEndMinusOneDisplay": "30/06/2014",
    "amalgamatedLoanNotPaidByEOIYFormatted": "$39.48",
    "openingBalancePayDays": "315",
    "openingBalanceInterestFormatted": "$2.03",
    "totalAmountOfRepaymentFormatted": "$39.48",
    "totalInterestFormatted": "$2.03",
    "principalFormatted": "$37.45",
    "enquiryYearEndDisplay": "30/06/2015",
    "minimumYearRepaymentFormatted": "$42.00"
  },
  "repayments": [
    {
      "rd": "12/5/2015",
      "ra": 39.483467207246576
    }
  ],
  "inputs": {
    "incomeYearOfLoan": 2010,
    "fullTermOfAmalgamatedLoan": 5,
    "incomeYearOfEnquiring": 2015,
    "amalgamatedLoanNotPaidByEOIY": 39.48346720724659,
    "repayments": null,
    "lodgement_date": null
  },
  "idx": 2207
}