{
  "id": "2023-10-31T18:21:45.343Z0.3194838343154436",
  "alert": "Start of result\nResult\n\nMinimum yearly repayment met.\n\nThe amount of the loan not repaid at the end of income year 2013-14 is $2,366.93.\n\n\u000b\n\nThe amalgamated loan will not be taken to be a dividend because the total repayments made are equal to or greater than the minimum yearly repayment required for income year 2013-14.\n\nInterest received by the private company must be included in the income tax return for 2013-14.\n\nMinimum yearly repayment\n\n$6,045.00\n\nBenchmark interest rate\n\n6.2%\n\nOpening balance:\n\nDate: 30/06/2013\n\nBalance: $11,052.00\n\nDays: 241\n\nInterest: $452.44\n\nPayments\n\nDate: 27/02/2014\n\nAmount: $9,177.00\n\nBalance: $1,875.00\n\nDays: 124\n\nInterest: $39.49\n\n\n\n\nTotal repayments\n\n$9,177.00\n\nTotal interest\n\n$491.93\n\nTotal principal\n\n$8,685.07\n\nClosing balance\n\nDate: 30/06/2014\n\nBalance: $2,366.93",
  "outputs": {
    "enquiryRateFormatted": "6.2%",
    "enquiryYearEndMinusOneDisplay": "30/06/2013",
    "amalgamatedLoanNotPaidByEOIYFormatted": "$11,052.00",
    "openingBalancePayDays": "241",
    "openingBalanceInterestFormatted": "$452.44",
    "totalAmountOfRepaymentFormatted": "$9,177.00",
    "totalInterestFormatted": "$491.93",
    "principalFormatted": "$8,685.07",
    "enquiryYearEndDisplay": "30/06/2014",
    "minimumYearRepaymentFormatted": "$6,045.00",
    "loanAmountFormatted": "$2,366.93"
  },
  "repayments": [
    {
      "rd": "27/2/2014",
      "ra": 9177
    }
  ],
  "inputs": {
    "incomeYearOfLoan": 2010,
    "fullTermOfAmalgamatedLoan": 5,
    "incomeYearOfEnquiring": 2014,
    "amalgamatedLoanNotPaidByEOIY": 11052,
    "repayments": null,
    "lodgement_date": null
  },
  "idx": 3846
}