{
  "id": "2023-09-05T20:21:41.865Z0.9086340335349097",
  "alert": "Start of result\nResult\n\nMinimum yearly repayment met.\n\nThe amount of the loan not repaid at the end of income year 2021-22 is $0.45.\n\nThe amalgamated loan will not be taken to be a dividend because the total repayments made are equal to or greater than the minimum yearly repayment required for income year 2021-22.\n\nInterest received by the private company must be included in the income tax return for 2021-22.\n\nMinimum yearly repayment\n\n$16.00\n\nBenchmark interest rate\n\n4.52%\n\nOpening balance:\n\nDate: 30/06/2021\n\nBalance: $30.81\n\nDays: 117\n\nInterest: $0.45\n\nPayments\n\nDate: 26/10/2021\n\nAmount: $30.81\n\nBalance: $0\n\nDays: 248\n\nInterest: $0\n\n\n\n\nTotal repayments\n\n$30.81\n\nTotal interest\n\n$0.45\n\nTotal principal\n\n$30.36\n\nClosing balance\n\nDate: 30/06/2022\n\nBalance: $0.45",
  "outputs": {
    "enquiryRateFormatted": "4.52%",
    "enquiryYearEndMinusOneDisplay": "30/06/2021",
    "amalgamatedLoanNotPaidByEOIYFormatted": "$30.81",
    "openingBalancePayDays": "117",
    "openingBalanceInterestFormatted": "$0.45",
    "totalAmountOfRepaymentFormatted": "$30.81",
    "totalInterestFormatted": "$0.45",
    "principalFormatted": "$30.36",
    "enquiryYearEndDisplay": "30/06/2022",
    "minimumYearRepaymentFormatted": "$16.00"
  },
  "repayments": [
    {
      "rd": "26/10/2021",
      "ra": 30.811796769958164
    }
  ],
  "inputs": {
    "incomeYearOfLoan": 2017,
    "fullTermOfAmalgamatedLoan": 6,
    "incomeYearOfEnquiring": 2022,
    "amalgamatedLoanNotPaidByEOIY": 30.81179676995817,
    "repayments": null,
    "lodgement_date": null
  },
  "idx": 5891
}