{
  "id": "2023-09-04T22:18:28.527Z0.3803841143622677",
  "alert": "Start of result\nResult\n\nMinimum yearly repayment not met.\n\nThe amount of the loan not repaid at the end of income year 2006-07 is $1,184.87.\n\nThe private company may be taken to pay a dividend under Division 7A to the shareholder or shareholder's associate because the amount repaid during income year 2006-07 in relation to the amalgamated loan is less than the minimum yearly repayment required.\n\nInterest received by the private company must be included in the income tax return for 2006-07.\n\nMinimum yearly repayment\n\n$12,796.00\n\nBenchmark interest rate\n\n7.55%\n\nOpening balance:\n\nDate: 30/06/2006\n\nBalance: $11,898.00\n\nDays: 0\n\nInterest: $0\n\nPayments\n\nDate: 01/07/2006\n\nAmount: $9,090.00\n\nBalance: $2,808.00\n\nDays: 20\n\nInterest: $11.62\n\n\n\n\nDate: 21/07/2006\n\nAmount: $336.00\n\nBalance: $2,472.00\n\nDays: 100\n\nInterest: $51.13\n\n\n\n\nDate: 29/10/2006\n\nAmount: $1,404.00\n\nBalance: $1,068.00\n\nDays: 245\n\nInterest: $54.12\n\n\n\n\nTotal repayments\n\n$10,830.00\n\nTotal interest\n\n$116.87\n\nTotal principal\n\n$10,713.13\n\nClosing balance\n\nDate: 30/06/2007\n\nBalance: $1,184.87",
  "outputs": {
    "enquiryRateFormatted": "7.55%",
    "enquiryYearEndMinusOneDisplay": "30/06/2006",
    "amalgamatedLoanNotPaidByEOIYFormatted": "$11,898.00",
    "openingBalancePayDays": "0",
    "openingBalanceInterestFormatted": "$0",
    "totalAmountOfRepaymentFormatted": "$10,830.00",
    "totalInterestFormatted": "$116.87",
    "principalFormatted": "$10,713.13",
    "enquiryYearEndDisplay": "30/06/2007",
    "minimumYearRepaymentFormatted": "$12,796.00"
  },
  "repayments": [
    {
      "rd": "1/7/2006",
      "ra": 9090
    },
    {
      "rd": "21/7/2006",
      "ra": 336
    },
    {
      "rd": "29/10/2006",
      "ra": 1404
    }
  ],
  "inputs": {
    "incomeYearOfLoan": 2001,
    "fullTermOfAmalgamatedLoan": 6,
    "incomeYearOfEnquiring": 2007,
    "amalgamatedLoanNotPaidByEOIY": 11898,
    "repayments": null,
    "lodgement_date": null
  },
  "idx": 677
}