{
  "id": "2023-09-04T17:40:28.500Z0.6977386242657289",
  "alert": "Start of result\nResult\n\nMinimum yearly repayment not met.\n\nThe amount of the loan not repaid at the end of income year 2013-14 is $100,862,249.82.\n\nThe private company may be taken to pay a dividend under Division 7A to the shareholder or shareholder's associate because the amount repaid during income year 2013-14 in relation to the amalgamated loan is less than the minimum yearly repayment required.\n\nInterest received by the private company must be included in the income tax return for 2013-14.\n\nMinimum yearly repayment\n\n$55,168,227.00\n\nBenchmark interest rate\n\n6.2%\n\nOpening balance:\n\nDate: 30/06/2013\n\nBalance: $100,862,249.82\n\nDays: 0\n\nInterest: $0\n\nPayments\n\nDate: 01/07/2013\n\nAmount: $925.00\n\nBalance: $100,861,324.82\n\nDays: 85\n\nInterest: $1,456,271.73\n\n\n\n\nDate: 24/09/2013\n\nAmount: $6,517.00\n\nBalance: $100,854,807.82\n\nDays: 17\n\nInterest: $291,235.53\n\n\n\n\nDate: 11/10/2013\n\nAmount: $2,126.00\n\nBalance: $100,852,681.82\n\nDays: 263\n\nInterest: $4,505,489.94\n\n\n\n\nTotal repayments\n\n$9,568.00\n\nTotal interest\n\n$6,252,997.20\n\nTotal principal\n\n$0\n\nClosing balance\n\nDate: 30/06/2014\n\nBalance: $100,862,249.82",
  "outputs": {
    "enquiryRateFormatted": "6.2%",
    "enquiryYearEndMinusOneDisplay": "30/06/2013",
    "amalgamatedLoanNotPaidByEOIYFormatted": "$100,862,249.82",
    "openingBalancePayDays": "0",
    "openingBalanceInterestFormatted": "$0",
    "totalAmountOfRepaymentFormatted": "$9,568.00",
    "totalInterestFormatted": "$6,252,997.20",
    "principalFormatted": "$0",
    "enquiryYearEndDisplay": "30/06/2014",
    "minimumYearRepaymentFormatted": "$55,168,227.00"
  },
  "repayments": [
    {
      "rd": "1/7/2013",
      "ra": 925
    },
    {
      "rd": "24/9/2013",
      "ra": 6517
    },
    {
      "rd": "11/10/2013",
      "ra": 2126
    }
  ],
  "inputs": {
    "incomeYearOfLoan": 2012,
    "fullTermOfAmalgamatedLoan": 3,
    "incomeYearOfEnquiring": 2014,
    "amalgamatedLoanNotPaidByEOIY": 100862249.82671623,
    "repayments": null,
    "lodgement_date": null
  },
  "idx": 2452
}