{
  "id": "2023-09-07T01:45:57.436Z0.8825076317220872",
  "alert": "Start of result\nResult\n\nMinimum yearly repayment not met.\n\nThe amount of the loan not repaid at the end of income year 1999-00 is $3,023.72.\n\nThe private company may be taken to pay a dividend under Division 7A to the shareholder or shareholder's associate because the amount repaid during income year 1999-00 in relation to the amalgamated loan is less than the minimum yearly repayment required.\n\nInterest received by the private company must be included in the income tax return for 1999-00.\n\nMinimum yearly repayment\n\n$1,071.00\n\nBenchmark interest rate\n\n6.5%\n\nOpening balance:\n\nDate: 30/06/1999\n\nBalance: $3,077.00\n\nDays: 79\n\nInterest: $43.17\n\nPayments\n\nDate: 18/09/1999\n\nAmount: $241.00\n\nBalance: $2,836.00\n\nDays: 287\n\nInterest: $144.55\n\n\n\n\nTotal repayments\n\n$241.00\n\nTotal interest\n\n$187.72\n\nTotal principal\n\n$53.28\n\nClosing balance\n\nDate: 30/06/2000\n\nBalance: $3,023.72",
  "outputs": {
    "enquiryRateFormatted": "6.5%",
    "enquiryYearEndMinusOneDisplay": "30/06/1999",
    "amalgamatedLoanNotPaidByEOIYFormatted": "$3,077.00",
    "openingBalancePayDays": "79",
    "openingBalanceInterestFormatted": "$43.17",
    "totalAmountOfRepaymentFormatted": "$241.00",
    "totalInterestFormatted": "$187.72",
    "principalFormatted": "$53.28",
    "enquiryYearEndDisplay": "30/06/2000",
    "minimumYearRepaymentFormatted": "$1,071.00"
  },
  "repayments": [
    {
      "rd": "18/9/1999",
      "ra": 241
    }
  ],
  "inputs": {
    "incomeYearOfLoan": 1999,
    "fullTermOfAmalgamatedLoan": 3,
    "incomeYearOfEnquiring": 2000,
    "amalgamatedLoanNotPaidByEOIY": 3077,
    "repayments": null,
    "lodgement_date": "17/2/2000"
  },
  "idx": 2439
}