{
  "id": "2023-10-31T18:13:45.365Z0.9865950963142062",
  "alert": "Start of result\nResult\n\nMinimum yearly repayment met.\n\nThe amount of the loan not repaid at the end of income year 2015-16 is $3,618.20.\n\n\u000b\n\nThe amalgamated loan will not be taken to be a dividend because the total repayments made are equal to or greater than the minimum yearly repayment required for income year 2015-16.\n\nInterest received by the private company must be included in the income tax return for 2015-16.\n\nMinimum yearly repayment\n\n$4,519.00\n\nBenchmark interest rate\n\n5.45%\n\nOpening balance:\n\nDate: 30/06/2015\n\nBalance: $12,204.00\n\nDays: 134\n\nInterest: $243.51\n\nPayments\n\nDate: 12/11/2015\n\nAmount: $8,942.00\n\nBalance: $3,262.00\n\nDays: 232\n\nInterest: $112.69\n\n\n\n\nTotal repayments\n\n$8,942.00\n\nTotal interest\n\n$356.20\n\nTotal principal\n\n$8,585.80\n\nClosing balance\n\nDate: 30/06/2016\n\nBalance: $3,618.20",
  "outputs": {
    "enquiryRateFormatted": "5.45%",
    "enquiryYearEndMinusOneDisplay": "30/06/2015",
    "amalgamatedLoanNotPaidByEOIYFormatted": "$12,204.00",
    "openingBalancePayDays": "134",
    "openingBalanceInterestFormatted": "$243.51",
    "totalAmountOfRepaymentFormatted": "$8,942.00",
    "totalInterestFormatted": "$356.20",
    "principalFormatted": "$8,585.80",
    "enquiryYearEndDisplay": "30/06/2016",
    "minimumYearRepaymentFormatted": "$4,519.00",
    "loanAmountFormatted": "$3,618.20"
  },
  "repayments": [
    {
      "rd": "12/11/2015",
      "ra": 8942
    }
  ],
  "inputs": {
    "incomeYearOfLoan": 2011,
    "fullTermOfAmalgamatedLoan": 7,
    "incomeYearOfEnquiring": 2016,
    "amalgamatedLoanNotPaidByEOIY": 12204,
    "repayments": null,
    "lodgement_date": null
  },
  "idx": 3579
}