{
  "id": "2023-09-05T19:53:51.658Z0.16826686587379136",
  "alert": "Start of result\nResult\n\nMinimum yearly repayment met.\n\nThe amount of the loan not repaid at the end of income year 2017-18 is $69.82.\n\nThe amalgamated loan will not be taken to be a dividend because the total repayments made are equal to or greater than the minimum yearly repayment required for income year 2017-18.\n\nInterest received by the private company must be included in the income tax return for 2017-18.\n\nMinimum yearly repayment\n\n$481.00\n\nBenchmark interest rate\n\n5.3%\n\nOpening balance:\n\nDate: 30/06/2017\n\nBalance: $1,693.00\n\nDays: 284\n\nInterest: $69.82\n\nPayments\n\nDate: 11/04/2018\n\nAmount: $1,693.00\n\nBalance: $0\n\nDays: 81\n\nInterest: $0\n\n\n\n\nTotal repayments\n\n$1,693.00\n\nTotal interest\n\n$69.82\n\nTotal principal\n\n$1,623.18\n\nClosing balance\n\nDate: 30/06/2018\n\nBalance: $69.82",
  "outputs": {
    "enquiryRateFormatted": "5.3%",
    "enquiryYearEndMinusOneDisplay": "30/06/2017",
    "amalgamatedLoanNotPaidByEOIYFormatted": "$1,693.00",
    "openingBalancePayDays": "284",
    "openingBalanceInterestFormatted": "$69.82",
    "totalAmountOfRepaymentFormatted": "$1,693.00",
    "totalInterestFormatted": "$69.82",
    "principalFormatted": "$1,623.18",
    "enquiryYearEndDisplay": "30/06/2018",
    "minimumYearRepaymentFormatted": "$481.00"
  },
  "repayments": [
    {
      "rd": "11/4/2018",
      "ra": 1693
    }
  ],
  "inputs": {
    "incomeYearOfLoan": 2017,
    "fullTermOfAmalgamatedLoan": 4,
    "incomeYearOfEnquiring": 2018,
    "amalgamatedLoanNotPaidByEOIY": 1693,
    "repayments": null,
    "lodgement_date": "16/3/2018"
  },
  "idx": 4308
}